chimera_cli/__init__.py
chimera_cli/__main__.py
chimera_cli/api.py
chimera_cli/build.py
chimera_cli/configuration.py
chimera_cli/parsing.py
chimera_cli/yaml_config.py
chimera_cli-1.0.data/scripts/chimera
chimera_cli-1.0.data/scripts/chimerapy
lib/chimera_cli/__init__.py
lib/chimera_cli/__main__.py
lib/chimera_cli/api.py
lib/chimera_cli/configuration.py
lib/chimera_cli/parsing.py
lib/chimera_cli/yaml_config.py
chimera_cli-1.0.dist-info/METADATA
chimera_cli-1.0.dist-info/WHEEL
chimera_cli-1.0.dist-info/top_level.txt
chimera_cli-1.0.dist-info/RECORD
