Metadata-Version: 2.1
Name: chimera-cli
Version: 1.0
Summary: Command line interface for chimera
Home-page: UNKNOWN
Author: Me
License: UNKNOWN
Platform: UNKNOWN
Requires-Python: >=3.6
Requires-Dist: setuptools
Requires-Dist: requests
Requires-Dist: pyyaml
Requires-Dist: avro-python3
Requires-Dist: docker
Requires-Dist: git-python
Requires-Dist: watchdog
